pydeck_grid/__init__.py
pydeck_grid/colormap.py
pydeck_grid/contour.py
pydeck_grid/image.py
pydeck_grid/layer.py
pydeck_grid/legend.py
pydeck_grid/mask.py
pydeck_grid/particle.py
pydeck_grid/pcolor.py
pydeck_grid-0.9.1.post1.dist-info/AUTHORS.rst
pydeck_grid-0.9.1.post1.dist-info/LICENSE
pydeck_grid-0.9.1.post1.dist-info/METADATA
pydeck_grid-0.9.1.post1.dist-info/WHEEL
pydeck_grid-0.9.1.post1.dist-info/top_level.txt
pydeck_grid-0.9.1.post1.dist-info/RECORD
