Metadata-Version: 2.1
Name: pydeck-grid
Version: 0.9.1.post1
Summary: Pydeck layers for gridded data
Home-page: https://github.com/oceanum-io/pydeck_grid
Author: Oceanum Developers
Author-email: developers@oceanum.science
License: MIT license
Keywords: pydeck gridded xarray
Classifier: Development Status :: 2 - Pre-Alpha
Classifier: Intended Audience :: Developers
Classifier: License :: OSI Approved :: MIT License
Classifier: Natural Language :: English
Classifier: Programming Language :: Python :: 3
Classifier: Programming Language :: Python :: 3.6
Classifier: Programming Language :: Python :: 3.7
Classifier: Programming Language :: Python :: 3.8
License-File: LICENSE
License-File: AUTHORS.rst
Requires-Dist: pydeck>=0.9.1
Requires-Dist: xarray
Requires-Dist: orjson
Requires-Dist: matplotlib
